{
  "certificate_id": "cert_bronze_003",
  "subject_id": "agent.untrusted.bot",
  "subject_type": "agent",
  "level": "BRONZE",
  "issuer": "registry.openbase.main",
  "issued_at": "2026-06-01T00:00:00Z",
  "expires_at": "2026-09-01T00:00:00Z",
  "revoked_at": "2026-07-05T00:00:00Z",
  "revocation_reason": "Trust score dropped below BRONZE threshold",
  "trust_snapshot": {
    "score": 0.15,
    "evidence_count": 3
  },
  "signature": "ed25519:dGVzdF9jZXJ0X3NpZ25hdHVyZV9kYXRhX2Zvcl9kZW1vbnN0cmF0aW9u",
  "status": "revoked",
  "renewal_count": 1
}